{"dictionary":{"সুন্দর (ব্যক্তি)":{"meaning":"ハンサム","category":"adjective","dateAdded":"2025-06-23T21:07:05.056Z"},"সুন্দর/পরিষ্কার":{"meaning":"きれい","category":"adjective","dateAdded":"2025-06-23T21:07:15.940Z"},"শান্ত":{"meaning":"しずか","category":"adjective","dateAdded":"2025-06-23T21:07:27.888Z"},"জমজমাট":{"meaning":"にぎやか","category":"adjective","dateAdded":"2025-06-23T21:07:42.615Z"},"বিখ্যাত":{"meaning":"ゆうめい","category":"adjective","dateAdded":"2025-06-23T21:07:55.567Z"},"দয়ালু":{"meaning":"しんせつ","category":"adjective","dateAdded":"2025-06-23T21:08:10.213Z"},"সুস্থ / প্রাণবন্ত":{"meaning":"げんき","category":"adjective","dateAdded":"2025-06-23T21:08:25.805Z"},"ফ্রি (সময়)":{"meaning":"ひま","category":"adjective","dateAdded":"2025-06-23T21:08:38.924Z"},"সুবিধাজনক":{"meaning":"べんり","category":"adjective","dateAdded":"2025-06-23T21:09:40.930Z"},"চমৎকার":{"meaning":"すてき","category":"adjective","dateAdded":"2025-06-23T21:10:09.963Z"},"বড়":{"meaning":"おおきい","category":"adjective","dateAdded":"2025-06-23T21:10:21.830Z"},"ছোট":{"meaning":"ちいさい","category":"adjective","dateAdded":"2025-06-23T21:10:31.238Z"},"নতুন":{"meaning":"あたらしい","category":"adjective","dateAdded":"2025-06-23T21:10:41.867Z"},"পুরানো":{"meaning":"ふるい","category":"adjective","dateAdded":"2025-06-23T21:11:02.676Z"},"ভাল":{"meaning":"いい (よい)","category":"adjective","dateAdded":"2025-06-23T21:11:17.020Z"},"খারাপ":{"meaning":"わるい","category":"adjective","dateAdded":"2025-06-23T21:11:27.943Z"},"গরম":{"meaning":"あつい","category":"adjective","dateAdded":"2025-06-23T21:11:36.706Z"},"ঠান্ডা (তাপমাত্রা)":{"meaning":"さむい","category":"adjective","dateAdded":"2025-06-23T21:11:51.777Z"},"ঠান্ডা (স্পর্শে)":{"meaning":"つめたい","category":"adjective","dateAdded":"2025-06-23T21:12:09.097Z"},"কঠিন":{"meaning":"むずかしい","category":"adjective","dateAdded":"2025-06-23T21:12:17.485Z"},"সহজ":{"meaning":"やさしい","category":"adjective","dateAdded":"2025-06-23T21:12:30.614Z"},"দামি / উচ্চ":{"meaning":"たかい","category":"adjective","dateAdded":"2025-06-23T21:12:43.602Z"},"সস্তা":{"meaning":"やすい","category":"adjective","dateAdded":"2025-06-23T21:15:39.151Z"},"নিচু":{"meaning":"ひくい","category":"adjective","dateAdded":"2025-06-23T21:15:52.339Z"},"মজার":{"meaning":"おもしろい","category":"adjective","dateAdded":"2025-06-23T21:16:03.888Z"},"সুস্বাদু":{"meaning":"おいしい","category":"adjective","dateAdded":"2025-06-23T21:16:13.834Z"},"ব্যস্ত":{"meaning":"いそがしい","category":"adjective","dateAdded":"2025-06-23T21:16:23.162Z"},"আনন্দদায়ক":{"meaning":"たのしい","category":"adjective","dateAdded":"2025-06-23T21:16:40.217Z"},"সাদা":{"meaning":"しろい","category":"adjective","dateAdded":"2025-06-23T21:16:49.291Z"},"কালো":{"meaning":"くろい","category":"adjective","dateAdded":"2025-06-23T21:16:57.241Z"},"লাল":{"meaning":"あかい","category":"adjective","dateAdded":"2025-06-23T21:17:04.370Z"},"নীল":{"meaning":"あおい","category":"adjective","dateAdded":"2025-06-23T21:17:15.642Z"},"চেরি ফুল":{"meaning":"さくら","category":"noun","dateAdded":"2025-06-23T21:17:48.060Z"},"পাহাড়":{"meaning":"やま","category":"noun","dateAdded":"2025-06-23T21:17:59.564Z"},"শহর":{"meaning":"まち","category":"noun","dateAdded":"2025-06-23T21:18:07.384Z"},"খাবার":{"meaning":"たべもの","category":"noun","dateAdded":"2025-06-23T21:18:27.303Z"},"গাড়ি":{"meaning":"くるま","category":"noun","dateAdded":"2025-06-23T21:18:35.373Z"},"স্থান / জায়গা":{"meaning":"ところ","category":"adverb","dateAdded":"2025-06-23T21:18:49.929Z"},"ছাত্রাবাস":{"meaning":"りょう","category":"adverb","dateAdded":"2025-06-23T21:18:58.620Z"},"পড়াশোনা":{"meaning":"べんきょう","category":"","dateAdded":"2025-06-23T21:19:05.697Z"},"জীবন":{"meaning":"せいかつ","category":"","dateAdded":"2025-06-23T21:19:11.685Z"},"কাজ /পেশা":{"meaning":"しごと","category":"","dateAdded":"2025-06-23T21:19:17.232Z"},"কেমন":{"meaning":"どう","category":"","dateAdded":"2025-06-23T21:19:23.332Z"},"কোন ধরনের":{"meaning":"どんな","category":"","dateAdded":"2025-06-23T21:19:28.704Z"},"কোনটি":{"meaning":"どれ","category":"","dateAdded":"2025-06-23T21:19:34.824Z"},"খুব":{"meaning":"とても","category":"","dateAdded":"2025-06-23T21:19:45.871Z"},"তেমন নয় (নেতিবাচক)":{"meaning":"あまり","category":"","dateAdded":"2025-06-23T21:19:51.640Z"},"এবং":{"meaning":"そして","category":"","dateAdded":"2025-06-23T21:19:59.616Z"},"~, কিন্তু ~":{"meaning":"～が、～","category":"","dateAdded":"2025-06-23T21:20:10.311Z"},"আপনি কেমন আছেন?":{"meaning":"おげんきですか","category":"","dateAdded":"2025-06-23T21:20:24.528Z"},"হ্যাঁ, তাই তো":{"meaning":"そうですね","category":"","dateAdded":"2025-06-23T21:20:33.675Z"},"আপনি জাপানের জীবনে অভ্যস্ত হয়েছেন?":{"meaning":"にほんの せいかつに なれましたか","category":"","dateAdded":"2025-06-23T21:20:49.932Z"},"আরেক কাপ নেবেন?":{"meaning":"もう いっぱい いかがですか","category":"","dateAdded":"2025-06-23T21:20:58.642Z"},"না, ধন্যবাদ, যথেষ্ট হয়েছে":{"meaning":"いいえ、けっこうです","category":"","dateAdded":"2025-06-23T21:21:05.634Z"},"ইতিমধ্যে ~ হয়েছে":{"meaning":"もう ～です[ね]","category":"","dateAdded":"2025-06-23T21:21:15.673Z"},"এখন আস্তে আস্তে উঠতে হচ্ছে":{"meaning":"そろそろ しつれいします","category":"","dateAdded":"2025-06-23T21:21:23.983Z"},"আবার আসবেন":{"meaning":"また いらっしゃってください","category":"","dateAdded":"2025-06-23T21:21:33.756Z"},"ফুজি পর্বত":{"meaning":"ふじさん","category":"","dateAdded":"2025-06-23T21:21:39.072Z"},"বিয়াও হ্রদ":{"meaning":"びわこ","category":"","dateAdded":"2025-06-23T21:21:46.763Z"},"শাংহাই":{"meaning":"シャンハイ","category":"","dateAdded":"2025-06-23T21:21:53.980Z"},"\"সাতজন সামুরাই\" নামের ছায়াছবি":{"meaning":"しちにんの さむらい","category":"","dateAdded":"2025-06-23T21:22:03.750Z"},"কিনকাকুজি মন্দির":{"meaning":"きんかくじ","category":"","dateAdded":"2025-06-23T21:22:12.019Z"}},"weakWords":[]}